linepay/__init__.py
linepay/api.py
linepay/exceptions.py
linepay/util.py
line_pay-0.2.0.dist-info/LICENSE.txt
line_pay-0.2.0.dist-info/METADATA
line_pay-0.2.0.dist-info/WHEEL
line_pay-0.2.0.dist-info/top_level.txt
line_pay-0.2.0.dist-info/RECORD
