Metadata-Version: 2.1
Name: line-pay
Version: 0.2.0
Summary: LINE Pay API SDK for Python
Home-page: https://github.com/sumihiro3/line-pay-sdk-python
Author: Sumihiro Kagawa
Author-email: sumihiro@gmail.com
License: MIT
Keywords: LINE,LINE Pay
Platform: UNKNOWN
Classifier: Development Status :: 4 - Beta
Classifier: License :: OSI Approved :: MIT License
Classifier: Programming Language :: Python
Classifier: Programming Language :: Python :: 3.6
Classifier: Programming Language :: Python :: 3.7
Classifier: Topic :: Software Development
Requires-Dist: requests (>=2.22.0)
